README.md
setup.py
HOMarkov/__init__.py
HOMarkov/markov.py
HOMarkov.egg-info/PKG-INFO
HOMarkov.egg-info/SOURCES.txt
HOMarkov.egg-info/dependency_links.txt
HOMarkov.egg-info/not-zip-safe
HOMarkov.egg-info/requires.txt
HOMarkov.egg-info/top_level.txt
test/__init__.py
test/test_HOM.py