Metadata-Version: 1.0
Name: HOMarkov
Version: 0.5.0
Summary: High Order Markov Chain model
Home-page: https://github.com/iz4vve/HOMarkov
Author: Pietro Mascolo
Author-email: iz4vve@gmail.com
License: GPL3
Platform: any
